Workbook
Name Growth: Inputs!$B$4
Name GrossMargin: Inputs!$B$5
Name Inflation: Inputs!$B$7
Name TaxRate: Inputs!$B$8

Sheet Summary
A1: Northwind Trading: summary
A3: Metric | B3: FY2027 | C3: Growth a year from FY2024 | D3: Total FY2024 to FY2027
A4: Revenue | B4: =Model!E4 -> 1597.2 | C4: =(Model!E4/Model!B4)^(1/3)-1 -> 0.1 | D4: =SUM(Model!B4:E4) -> 5569.2
A5: EBIT | B5: =Model!E8 -> 332.07863 | C5: =(Model!E8/Model!B8)^(1/3)-1 -> 0.19622553 | D5: =SUM(Model!B8:E8) -> 1042.1396
A6: Net income | B6: =Model!E12 -> 249.05897 | C6: =(Model!E12/Model!B12)^(1/3)-1 -> 0.19622553 | D6: =SUM(Model!B12:E12) -> 781.60472

Sheet Model
A1: Northwind Trading: operating model
A3: £k | B3: FY2024 | C3: FY2025 | D3: FY2026 | E3: FY2027
A4: Revenue | B4: =SUM(Customers[Revenue FY2024]) -> 1200 | C4: =B4*(1+Growth) -> 1320 | D4: =C4*(1+Growth) -> 1452 | E4: =D4*(1+Growth) -> 1597.2
A5: Growth | C5: =C4/B4-1 -> 0.1 | D5: =D4/C4-1 -> 0.1 | E5: =E4/D4-1 -> 0.1
A6: Gross profit | B6: =B4*GrossMargin -> 504 | C6: =C4*GrossMargin -> 554.4 | D6: =D4*GrossMargin -> 609.84 | E6: =E4*GrossMargin -> 670.824
A7: Operating costs | B7: =Inputs!B6 -> 310 | C7: =B7*(1+Inflation) -> 319.3 | D7: =C7*(1+Inflation) -> 328.879 | E7: =D7*(1+Inflation) -> 338.74537
A8: EBIT | B8: =B6-B7 -> 194 | C8: =C6-C7 -> 235.1 | D8: =D6-D7 -> 280.961 | E8: =E6-E7 -> 332.07863
A9: EBIT margin | B9: =B8/B4 -> 0.16166667 | C9: =C8/C4 -> 0.17810606 | D9: =D8/D4 -> 0.19349931 | E9: =E8/E4 -> 0.20791299
A11: Tax | B11: =-B8*TaxRate -> -48.5 | C11: =-C8*TaxRate -> -58.775 | D11: =-D8*TaxRate -> -70.24025 | E11: =-E8*TaxRate -> -83.019658
A12: Net income | B12: =B8+B11 -> 145.5 | C12: =C8+C11 -> 176.325 | D12: =D8+D11 -> 210.72075 | E12: =E8+E11 -> 249.05897

Sheet Inputs
A1: Northwind Trading: assumptions
A3: Assumption | B3: Value | C3: Unit
A4: Revenue growth | B4: 0.1 | C4: a year
A5: Gross margin | B5: 0.42 | C5: of revenue
A6: Operating costs FY2024 | B6: 310 | C6: £k
A7: Cost inflation | B7: 0.03 | C7: a year
A8: Tax rate | B8: 0.25 | C8: of EBIT

Sheet Customers
A1: Customer | B1: Region | C1: Revenue FY2024
A2: Alder Foods | B2: North | C2: 310
A3: Birch Retail | B3: South | C3: 285
A4: Cedar Hotels | B4: North | C4: 240
A5: Damson Cafés | B5: West | C5: 205
A6: Elm Wholesale | B6: South | C6: 160

Sheet Scratch
A1: Old scenario, not used
A2: Revenue growth | B2: 0.15
